tableMulti_anneeBiss
