Metadata-Version: 2.1
Name: tableMulti-anneeBiss
Version: 0.0.2
Summary: Le package tableMulti_anneeBiss contient deux modules annee_bissextile & table_multiplication
Home-page: https://github.com/OusmaneCisse/tableMulti_anneeBiss
Author: Ousmane CISSE
Author-email: boutross64@gmail.com
License: WTFPL
Platform: UNKNOWN
Classifier: Programming Language :: Python
Classifier: Development Status :: 1 - Planning
Classifier: License :: OSI Approved
Classifier: Natural Language :: French
Classifier: Operating System :: OS Independent
Classifier: Programming Language :: Python :: 3
Classifier: Topic :: Communications
